{"0": "A-Lin", "2": "Adira", "3": "Adrian Minune", "4": "Afgan", "6": "Ai", "9": "Aiko", "10": "Aimer", "13": "Albert West", "14": "Alex Mica", "15": "Alexandra Stan", "16": "Alma", "17": "Alya", "20": "Amel Bent", "21": "Am\u00e1lia Rodrigues", "22": "Ana Gabriel", "24": "Anah\u00ed", "27": "Annabel", "28": "Anneke Gr\u00f6nloh", "31": "Antonio Aguilar", "32": "Ant\u00f3nio Varia\u00e7\u00f5es", "33": "Anuar Zain", "35": "Ari Lasso", "36": "Arun Thapa", "37": "Aruna Lama", "40": "Aya Nakamura", "41": "Ayu Ting Ting", "43": "Barbara", "45": "Beni", "46": "Bernadette", "50": "Boris", "53": "Bourvil", "55": "Brigitte Bardot", "56": "Broery Marantika", "57": "Bunga Citra Lestari", "58": "C. J\u00e9r\u00f4me", "59": "Cali", "60": "Camelia", "62": "Carla Bruni", "63": "Carla Morrison", "64": "Carlos", "66": "Caro Emerald", "70": "Centerfold", "73": "Charles Aznavour", "74": "Charles Tr\u00e9net", "75": "Charlotte Gainsbourg", "79": "Christian Nodal", "80": "Christophe Ma\u00e9", "81": "Chrisye", "82": "Cinta Laura", "83": "Cita Citata", "85": "Claudine Longet", "89": "Corina", "90": "Cornelis Vreeswijk", "91": "Corynne Charby", "92": "Cristian Castro", "93": "Crowd Lu", "94": "Daichi Miura", "95": "Dalida", "96": "Daniela Romo", "97": "Danna Paola", "98": "Dany Brillant", "99": "Dave", "101": "David Z\u00e1izar", "102": "Debbie", "103": "Dewi Sandra", "104": "Dewiq", "105": "Dhiraj Rai", "107": "Do", "109": "Ebiet G Ade", "111": "EliZe", "119": "Fanny", "121": "Fernando Machado Soares", "122": "Fey", "123": "Florin Salam", "125": "Garou", "126": "George Baker", "127": "Gilbert B\u00e9caud", "128": "Gita Gutawa", "129": "Glenn Fredly", "130": "Gombloh", "132": "Guadalupe Pineda", "135": "Haruka Tomatsu", "137": "Hikaru Utada", "138": "ITSUKA", "139": "Imran Khan", "140": "Indah Dewi Pertiwi", "141": "Indila", "142": "Inna", "143": "Inul Daratista", "144": "Isabelle Adjani", "146": "Isyana Sarasvati", "147": "Iwa K", "148": "Iwan Fals", "150": "Jain", "152": "Javier Sol\u00eds", "156": "Jenni Vartiainen", "158": "Joe Dassin", "159": "Johnny Hallyday", "160": "Jolin Tsai", "161": "Josephine Baker", "162": "Jos\u00e9 Jos\u00e9", "163": "Juan Gabriel", "164": "Juju", "165": "Julieta Venegas", "167": "Kalimba", "168": "Kamal Khatri", "169": "Kang Kang", "171": "Kendji Girac", "172": "Keren Ann", "174": "Kunti Moktan", "177": "Lay Low", "178": "Leslie", "179": "LiSA", "181": "Lila Downs", "182": "Lisa", "185": "Lo\u00efs Lane", "187": "Lucero", "188": "Lucienne Boyer", "190": "Luis Miguel", "191": "Lura", "193": "L\u00e9o Ferr\u00e9", "196": "Maaya Sakamoto", "197": "Maki Ohguro", "199": "Marcha", "200": "Marco Antonio Sol\u00eds", "201": "Marco Borsato", "204": "Maribel Guardia", "207": "Mar\u00eda Jos\u00e9", "209": "Maurice Chevalier", "210": "Mawi", "212": "May'n", "213": "Ma\u00eetre Gims", "214": "Melly Goeslaw", "217": "Mia", "218": "Mihai Traistariu", "219": "Mike Mohede", "220": "Mikuni Shimokawa", "221": "Miss Montreal", "222": "Miwa", "226": "Nabin K Bhattarai", "227": "Nafa Urbach", "228": "Naghma", "229": "Namie Amuro", "230": "Narayan Gopal", "231": "Natalie La Rose", "232": "Nicky Astria", "233": "Nike Ardilla", "234": "Niki", "235": "Nima Rumba", "236": "Noraniza Idris", "237": "N\u00e2diya", "238": "Once", "239": "Passi", "241": "Patrick Bruel", "242": "Paulina Rubio", "244": "Pedro Fern\u00e1ndez", "245": "Pedro Infante", "246": "Pete Teo", "247": "Petula Clark", "251": "Raju Lama", "252": "Ram Krishna Dhakal", "255": "Ray", "256": "Renaud", "257": "Rich Brian", "258": "Rikki", "259": "Rita", "260": "Rita Guerra", "261": "Rizky Febian", "262": "Robert", "263": "Rossa", "264": "Ruth Sahanaya", "265": "Sabrina", "268": "Samo", "271": "Selena", "272": "Serge Gainsbourg", "274": "Shambhu Rai", "275": "Sheila", "276": "Shela", "280": "Shaan", "281": "Siti Nurhaliza", "283": "Stanislas", "284": "Suara", "285": "Sugam Pokharel", "287": "Suzy", "288": "Syahrini", "290": "S\u00e9bastien Tellier", "292": "S\u00f3ley", "293": "Taco", "295": "Tara Devi", "296": "Tatiana", "299": "Tino Rossi", "300": "Titi DJ", "301": "Titiek Puspa", "302": "Tsuki Amano", "304": "Ua", "305": "Udit Narayan", "307": "Vidi Aldiano", "309": "Vina Panduwinata", "311": "Waylon", "316": "Yo", "317": "Yui", "319": "Yuni Shara", "320": "Yura Yunita", "322": "Yves Montand", "324": "Zaq", "325": "Zaz", "327": "Zee Avi", "328": "Ziana Zain", "333": "Aaliyah", "335": "Ace of Base", "336": "Adam Ant", "337": "Adam Lambert", "338": "Adam Levine", "339": "Adele", "341": "Akon", "342": "Al Green", "343": "Al Hibbler", "344": "Al Jarreau", "345": "Al Jolson", "346": "Alan Jackson", "348": "Alanis Morissette", "349": "Alannah Myles", "350": "Alejandro Fern\u00e1ndez", "351": "Alex Chilton", "352": "Alexander O'Neal", "353": "Alice Cooper", "354": "Alison Krauss", "355": "Allison Crowe", "356": "Alvin Lee", "358": "Amanda Palmer", "359": "Amanda Seyfried", "360": "Amber", "361": "Amy Lee", "363": "Amy Millan", "364": "Amy Winehouse", "365": "Andrea Echeverri", "366": "Andrew Wood", "367": "Andy Partridge", "368": "Andy Williams", "369": "Ane Brun", "370": "Ani DiFranco", "371": "Anna Tsuchiya", "372": "Anne Hathaway", "373": "Annie Lennox", "374": "Anouk", "375": "Anthony Green", "378": "Aretha Franklin", "379": "Ariana Grande", "380": "Arijit Singh", "381": "Art Garfunkel", "382": "Arthur Prysock", "383": "Asha Bhosle", "384": "Ashanti", "387": "Avril Lavigne", "388": "Ayumi Hamasaki", "390": "Barbara Cook", "391": "Barbra Streisand", "392": "Barry Manilow", "393": "Beach House", "394": "Becca", "395": "Beck", "396": "Ben E. King", "397": "Ben Folds", "398": "Ben Platt", "399": "Bernadette Peters", "400": "Beth Hart", "401": "Bette Midler", "402": "Beverley Craven", "403": "Beyonc\u00e9", "406": "Bill Henderson", "408": "Bill Withers", "409": "Billie Eilish", "410": "Billie Myers", "412": "Billy Eckstine", "413": "Billy Idol", "414": "Billy Joel", "416": "Bing Crosby", "417": "Birdy", "418": "Bizzy Bone", "419": "Bj\u00f6rk", "420": "Blake Shelton", "421": "Blossom Dearie", "423": "Bob Crosby", "424": "Bob Geldof", "425": "Bob Hope", "426": "Bob Marley", "428": "Bob Seger", "429": "Bobby Caldwell", "430": "Bobby Fuller", "431": "Bobby McFerrin", "432": "Bobby Womack", "434": "Bonnie Raitt", "436": "Bono", "437": "Boy George", "438": "Brady Seals", "439": "Brandon Flowers", "440": "Brenda Lee", "441": "Brendan Perry", "443": "Brendon Urie", "444": "Brett Anderson", "445": "Brian May", "448": "Bridgit Mendler", "449": "Britney Spears", "451": "Bruce Springsteen", "452": "Bruno Mars", "453": "Bryan Adams", "454": "Bryan Ferry", "455": "Burton Cummings", "456": "Cab Calloway", "457": "Calvin Harris", "458": "Calvin Johnson", "459": "Camila Cabello", "460": "Cara Dillon", "461": "Carla Bozulich", "462": "Carly Rae Jepsen", "463": "Carly Simon", "464": "Carole King", "466": "Carrie Underwood", "467": "Cat Power", "468": "Cat Stevens", "469": "Celine Dion", "470": "Chaka Khan", "471": "Chantal Kreviazuk", "472": "Charlie Puth", "473": "Charlotte Church", "475": "Cher", "477": "Cheryl", "478": "Chet Baker", "479": "Childish Gambino", "480": "Chilli", "481": "Chris Brown", "482": "Chris Cornell", "483": "Chris Isaak", "486": "Christina Aguilera", "487": "Christina Milian", "488": "Christina Perri", "489": "Christine McVie", "491": "Clay Aiken", "492": "Coko", "494": "Connie Francis", "495": "Conor Oberst", "496": "Conway Twitty", "498": "Cranes", "500": "Crystal Gayle", "501": "Curtis Stigers", "503": "Cyndi Lauper", "504": "Dallas Green", "505": "Damien Rice", "507": "Dan Wilson", "508": "Dana Fuchs", "509": "Daniel O'Donnell", "510": "Darius Rucker", "511": "Darlene Love", "513": "Daryl Hall", "514": "Dave Matthews", "515": "David Archuleta", "516": "David Bowie", "517": "David Byrne", "518": "David Gates", "520": "David Johansen", "522": "David Ruffin", "525": "Dean Martin", "526": "Deanna Durbin", "527": "Demi Lovato", "528": "Demis Roussos", "529": "Deniece Williams", "530": "Destiny's Child", "531": "Devin Townsend", "532": "Diana Ross", "533": "Dido", "535": "Dionne Warwick", "536": "Divinyls", "537": "Dizzy Gillespie", "539": "Dolly Parton", "540": "Dolores O'Riordan", "541": "Dolores O\u2019Riordan", "542": "Don Henley", "543": "Don Redman", "544": "Don Williams", "545": "Donna Summer", "547": "Donny Hathaway", "548": "Dorinda Clark-Cole", "549": "Dorothy Martin", "550": "Drake", "551": "Dua Lipa", "553": "Dusty Springfield", "555": "Ed Sheeran", "556": "Eddi Reader", "557": "Eddie Kendricks", "558": "Eddie Vedder", "559": "Edwyn Collins", "560": "El DeBarge", "561": "Ella", "562": "Ella Fitzgerald", "563": "Elle King", "564": "Ellie Goulding", "565": "Elton John", "566": "Elvis Presley", "567": "Emeli Sand\u00e9", "568": "Emmylou Harris", "569": "Enya", "570": "Eric Burdon", "571": "Eric Clapton", "572": "Ernie Haase", "573": "Esperanza Spalding", "574": "Ethel Merman", "575": "Etta James", "576": "Eva Cassidy", "578": "Eydie Gorm\u00e9", "579": "FKA Twigs", "580": "Fats Domino", "581": "Fetty Wap", "582": "Fish", "583": "Fleetwood Mac", "584": "Flor", "585": "Frank Black", "586": "Frank Ocean", "587": "Frank Sinatra", "588": "Frankie Laine", "589": "Frankie Valli", "590": "Fred Astaire", "592": "Fred Schneider", "593": "Freddie Mercury", "595": "Gary Barlow", "596": "Gary Numan", "597": "Gary Puckett", "599": "Gene Simmons", "600": "George Benson", "601": "George Harrison", "602": "George Michael", "603": "George Thorogood", "604": "Gerry Rafferty", "605": "Gibby Haynes", "606": "Ginger", "607": "Gladys Knight", "608": "Glen Campbell", "609": "Glenn Frey", "610": "Glenn Kaiser", "611": "Glenn Tilbrook", "612": "Gloria Jones", "613": "Gordon Lightfoot", "616": "Greg Lake", "617": "Gregg Allman", "618": "Grimes", "619": "Gwen Stefani", "621": "Harry Belafonte", "622": "Harry Nilsson", "623": "Harry Styles", "624": "Hayley Westenra", "625": "Hazel O'Connor", "627": "Hoagy Carmichael", "628": "Hole", "630": "Hope Sandoval", "632": "Hot Lips Page", "634": "Hozier", "635": "Hugh Masekela", "638": "Ian Dury", "639": "Ian Hunter", "640": "Ibrahim Tatlises", "643": "Iggy Pop", "644": "Ingrid Michaelson", "645": "Irma Thomas", "646": "J Balvin", "647": "J. Cole", "649": "Jack Black", "650": "Jack Jones", "653": "Jack White", "654": "Jackie Wilson", "655": "James Blake", "657": "James Brown", "658": "James Taylor", "660": "Jane Siberry", "662": "Janelle Mon\u00e1e", "663": "Janet Jackson", "665": "Janis Joplin", "666": "Jarvis Cocker", "667": "Jay McShann", "668": "Jeff Buckley", "669": "Jeff Martin", "671": "Jefferson Airplane", "672": "Jeffrey Osborne", "673": "Jello Biafra", "674": "Jennifer Hudson", "676": "Jennifer Rush", "677": "Jenny Lewis", "678": "Jerry Garcia", "679": "Jessica Simpson", "680": "Jessie J", "682": "Jill Scott", "685": "Jim Morrison", "686": "Jim Nabors", "687": "Jim Reeves", "688": "Jimi Hendrix", "689": "Jimmy Barnes", "690": "Jimmy Cliff", "691": "Jimmy Rushing", "692": "Jimmy Scott", "694": "JoJo", "695": "Joan Armatrading", "696": "Joan As Police Woman", "697": "Joan Baez", "698": "Joan Jett", "700": "Joe Cocker", "702": "Joe Walsh", "703": "Joe Williams", "706": "John Butler", "707": "John Cougar Mellencamp", "708": "John Denver", "709": "John Fogerty", "710": "John Legend", "711": "John Lennon", "712": "John Mayer", "715": "John Waite", "717": "Johnny Cash", "718": "Johnny Hartman", "719": "Johnny Mathis", "720": "Joji", "722": "Jonah Matranga", "723": "Jonalyn Viray", "724": "Jonathan Davis", "725": "Joni Mitchell", "727": "Josh Groban", "728": "Juanes", "729": "Judy Collins", "730": "Juice Newton", "731": "Juka", "732": "Julee Cruise", "733": "Julian Casablancas", "734": "Julian Cope", "735": "Juliana Hatfield", "736": "Julie Andrews", "737": "Julie Doiron", "738": "Julie Driscoll", "739": "Julie London", "740": "Justin Bieber", "741": "Justin Hayward", "743": "Justin Timberlake", "744": "KT Tunstall", "745": "Kane Brown", "748": "Kathleen Hanna", "749": "Katie Herzig", "750": "Katy B", "751": "Kehlani", "752": "Keith Morris", "753": "Kelis", "754": "Kellie Pickler", "755": "Kelly Clarkson", "757": "Kelly Rowland", "759": "Kenny Loggins", "761": "Kenny Rogers", "763": "Kevin Mahogany", "764": "Keyshia Cole", "765": "Khalid", "767": "Kierra Sheard", "768": "Kiesza", "769": "Kim Carnes", "770": "King Diamond", "771": "King Pleasure", "772": "Kirsty MacColl", "773": "Koko Taylor", "776": "Kylie Minogue", "778": "La Diva", "782": "Lara Fabian", "784": "Laura Branigan", "786": "Laura Pausini", "789": "Lea Michele", "790": "Lea Salonga", "791": "Lee Ranaldo", "792": "Lemmy", "794": "Leona Lewis", "795": "Leonard Nimoy", "797": "Lesley Gore", "798": "Liam Gallagher", "799": "Lights", "800": "Lily Allen", "801": "Lina", "802": "Linda Eder", "803": "Linda Ronstadt", "804": "Linda Thompson", "805": "Lionel Hampton", "808": "Lita Ford", "809": "Little Annie", "810": "Little Eva", "811": "Little Richard", "814": "Lorde", "816": "Lou Rawls", "817": "Lou Reed", "819": "Louis Armstrong", "820": "Louis Jordan", "821": "Louis Prima", "822": "Lowell George", "824": "Lucinda Williams", "828": "Lush", "829": "Luther Vandross", "830": "Lykke Li", "831": "MIKA", "832": "Madonna", "833": "Maluma", "834": "Marc Almond", "835": "Marc Anthony", "836": "Marc Bolan", "838": "Maria Muldaur", "840": "Mariah Carey", "841": "Marianne Faithfull", "842": "Marie Osmond", "843": "Marilyn Manson", "844": "Marion Williams", "846": "Mark Knopfler", "848": "Mark Lowry", "851": "Martha Reeves", "852": "Martha Wainwright", "853": "Martha Wash", "854": "Martha and the Vandellas", "855": "Martina McBride", "856": "Marty Casey", "857": "Marvin Gaye", "858": "Mary Chapin Carpenter", "864": "Maureen McGovern", "865": "Maurice White", "867": "Meat Loaf", "868": "Mel Torm\u00e9", "869": "Melanie Martinez", "871": "Melissa Ferrick", "873": "Michael Bolton", "874": "Michael Bubl\u00e9", "875": "Michael Crawford", "876": "Michael Feinstein", "877": "Michael Hutchence", "878": "Michael Jackson", "879": "Michael McDonald", "880": "Michael Tait", "881": "Michelle Branch", "884": "Mick Jagger", "885": "Mick Jones", "886": "Micky Dolenz", "887": "Midge Ure", "889": "Mike Posner", "890": "Mike Tramp", "891": "Miles Hunt", "892": "Miley Cyrus", "895": "Minnie Riperton", "897": "Morrissey", "898": "Mose Allison", "899": "Myl\u00e8ne Farmer", "901": "Nana Mouskouri", "902": "Nanci Griffith", "904": "Nancy Wilson", "905": "Nat King Cole", "906": "Natalie Cole", "907": "Nate Dogg", "908": "Nate Ruess", "909": "Ne-Yo", "910": "Neige", "911": "Neil Diamond", "912": "Neil Young", "913": "Neko Case", "914": "Nelly Furtado", "915": "Nena", "916": "Nergal", "917": "Nick Cave", "918": "Nick Drake", "919": "Nick Heyward", "920": "Nick Jonas", "921": "Nick Lucas", "922": "Nico", "923": "Nicole C. Mullen", "924": "Nicole Scherzinger", "925": "Niki Barr", "926": "Nina Hagen", "927": "Nina Simone", "929": "Norah Jones", "931": "Nusrat Fateh Ali Khan", "933": "Ofra Haza", "935": "Olivia Newton-John", "938": "Ozzy Osbourne", "939": "PJ Harvey", "940": "Pat Benatar", "941": "Patti LaBelle", "942": "Patti Smith", "943": "Patty Griffin", "944": "Patty Smyth", "946": "Paul McCartney", "949": "Paul Stanley", "950": "Paul Weller", "951": "Paul Westerberg", "952": "Paul Williams", "955": "Peabo Bryson", "957": "Perry Como", "959": "Pete Townshend", "961": "Peter Gabriel", "963": "Phil Collins", "964": "Philip Bailey", "965": "Poe", "966": "Porcelain Black", "967": "Portishead", "968": "Post Malone", "969": "R. Kelly", "971": "Rachel Sweet", "972": "Rahat Fateh Ali Khan", "974": "Ralph Tresvant", "977": "Randy Travis", "978": "Ray Charles", "980": "Regina Spektor", "981": "Richard Ashcroft", "982": "Richard Thompson", "983": "Rick Astley", "984": "Rickie Lee Jones", "985": "Ricky Martin", "986": "Rico Blanco", "987": "Rihanna", "988": "Ringo Starr", "989": "Rita Lee", "990": "Rita Ora", "991": "Rivers Cuomo", "992": "Rob Zombie", "993": "Robert Goulet", "994": "Robert Palmer", "995": "Robert Plant", "999": "Robin Gibb", "1000": "Robin Zander", "1001": "Robyn", "1002": "Rod Stewart", "1003": "Ronald Isley", "1004": "Ronan Keating", "1005": "Ronnie Dunn", "1007": "Roy Orbison", "1008": "Rudy Vallee", "1009": "Rufus", "1010": "Rufus Wainwright", "1012": "Ruth Brown", "1013": "Ryan Adams", "1015": "Sade", "1017": "Sam Cooke", "1018": "Sam Smith", "1020": "Sammy Davis Jr.", "1021": "Sammy Hagar", "1022": "Sandi Patty", "1024": "Sandy Denny", "1025": "Santigold", "1026": "Sara Bareilles", "1029": "Scott Walker", "1031": "Selena Gomez", "1032": "Shawn Mendes", "1033": "Sheena Easton", "1034": "Sheryl Crow", "1035": "Shirley Caesar", "1037": "Shreya Ghoshal", "1038": "Sigrid", "1040": "Sister Rosetta Tharpe", "1041": "Skeeter Davis", "1042": "Skin", "1044": "Slim Gaillard", "1046": "Smokey Robinson", "1047": "Solomon Burke", "1049": "Stephanie", "1050": "Stephanie Mills", "1051": "Stephen Malkmus", "1052": "Steve Marriott", "1053": "Steve Miller", "1054": "Steve Winwood", "1055": "Stevie Nicks", "1056": "Stevie Ray Vaughan", "1057": "Stevie Wonder", "1058": "Sting", "1059": "Stromae", "1063": "Sunny", "1065": "Susan Tedeschi", "1066": "Susanna Wallumr\u00f8d", "1069": "Swae Lee", "1071": "Syd Barrett", "1072": "TLC", "1073": "Taeyang", "1074": "Tamela Mann", "1075": "Tammy Wynette", "1077": "Taylor Hawkins", "1078": "Teddy Pendergrass", "1079": "Teena Marie", "1080": "Terri Nunn", "1083": "Teru", "1084": "Tevin Campbell", "1087": "The Andrews Sisters", "1088": "The Carpenters", "1089": "The Chainsmokers", "1095": "The Marcels", "1096": "The Platters", "1097": "The Pointer Sisters", "1101": "The Velvet Underground", "1102": "The Veronicas", "1103": "The Weavers", "1104": "The Weeknd", "1106": "Thomas Anders", "1107": "Tiffany", "1108": "Timothy B. Schmit", "1109": "Tina Turner", "1111": "Tiwa Savage", "1112": "Toby Keith", "1114": "Tom Jones", "1115": "Tom Petty", "1117": "Tony Bennett", "1118": "Tony Hadley", "1119": "Tony Martin", "1120": "Tori Amos", "1121": "Tori Kelly", "1122": "Toshi", "1123": "Tove Lo", "1126": "Trey Anastasio", "1127": "Trey Songz", "1128": "Troye Sivan", "1129": "Tyler Joseph", "1130": "Usher", "1131": "Ute Lemper", "1132": "V", "1133": "Vanessa Bell Armstrong", "1134": "Vanessa Paradis", "1135": "Vera Lynn", "1138": "Waje", "1139": "Wanda Jackson", "1140": "Warren Zevon", "1141": "Waylon Jennings", "1142": "We Are the Fallen", "1143": "Wendy", "1144": "Whitney Houston", "1145": "Willie Nelson", "1148": "Yma Sumac", "1150": "Yolanda Adams", "1151": "Youssou N'Dour", "1152": "Zara Larsson", "1153": "Zola Jesus", "1154": "will.i.am", "1155": "\u00c9dith Piaf", "1156": "\u015eebnem Ferah", "1157": "Michael Stipe", "1159": "Moya Brennan", "1160": "Paul Smith", "1161": "Ian McCulloch", "1162": "Chris Martin", "1164": "Simon Le Bon", "1165": "Aaron Hall", "1166": "Zack de la Rocha", "1167": "Gordon Gano", "1169": "Jon Foreman", "1171": "Linda Perry", "1173": "Vic Ruggiero", "1174": "Colin Hay", "1175": "Wayne Coyne", "1176": "Randy Owen", "1177": "Sebastian Bach", "1178": "Aaron Lewis", "1180": "Kim Wilson", "1183": "Tom Keifer", "1184": "Maynard James Keenan", "1185": "Keith Relf", "1187": "James \"J.T.\" Taylor", "1189": "Paul Banks", "1190": "Levi Stubbs", "1194": "M. Shadows", "1195": "Sarah Cracknell", "1196": "Don Dokken", "1197": "Gavin Rossdale", "1198": "Peter Murphy", "1200": "Stephen Christian", "1201": "Jon Anderson", "1202": "Donald Fagen", "1204": "Big Kenny", "1208": "David Usher", "1210": "Bret Michaels", "1213": "Raul Malo", "1220": "Darren Hayes", "1221": "Scott Weiland", "1226": "Tim Burgess", "1227": "Nina Persson", "1228": "Damon Albarn", "1229": "Justin Currie", "1230": "Natalie Maines", "1232": "Jon Bon Jovi", "1234": "Zakk Wylde", "1235": "Andi Deris", "1237": "Shane MacGowan", "1238": "Andy Bell", "1240": "Scott Stapp", "1242": "Kevin Rowland", "1246": "Charlie Wilson", "1247": "Jemina Pearl", "1250": "Alison Moyet", "1251": "Jeff Lynne", "1253": "Kevin DuBrow", "1254": "Roger Daltrey", "1258": "Brian Molko", "1259": "Max Cavalera", "1261": "Gordon Downie", "1263": "Bobby Gillespie", "1264": "Gary Louris", "1267": "John Kay", "1268": "Dave Gahan", "1271": "Dave Grohl", "1273": "Corey Taylor", "1274": "Fran Healy", "1277": "Cerys Matthews", "1278": "Tim Rogers", "1279": "Mickey Thomas", "1281": "Dee Snider", "1283": "Dave Pirner", "1284": "Mike Scott", "1285": "Ian Brown", "1286": "Colin Newman", "1288": "Paul King", "1290": "Tracey Thorn", "1292": "John Cooper", "1294": "Chad Kroeger", "1296": "Mark King", "1297": "Mark Mothersbaugh", "1299": "Steven Tyler", "1301": "Chino Moreno", "1302": "Roland Gift", "1303": "Stephen Pearcy", "1304": "Miho Hatori", "1305": "Chuck D", "1306": "Vince Neil", "1308": "Steven Wilson", "1309": "Aidan Moffat", "1313": "Neil Finn", "1314": "John Rzeznik", "1316": "Dave Cousins", "1317": "Deborah Harry", "1321": "Josh Homme", "1322": "Sully Erna", "1323": "Andrea Corr", "1325": "Jim Reid", "1326": "Dicky Barrett", "1328": "Patrick Stump", "1329": "Rob Thomas", "1331": "Chester Bennington", "1332": "Corey Glover", "1334": "Tunde Adebimpe", "1336": "David Draiman", "1337": "Tim Armstrong"}